printpkg/__init__.py
printpkg/texts.py
retrievepg-0.1.dist-info/METADATA
retrievepg-0.1.dist-info/WHEEL
retrievepg-0.1.dist-info/top_level.txt
retrievepg-0.1.dist-info/RECORD
