Metadata-Version: 2.4
Name: retrievepg
Version: 0.1
Summary: A simple package to print predefined texts
Author: Your Name
Author-email: your.email@example.com
Dynamic: author
Dynamic: author-email
Dynamic: summary
